README.rst
pyproject.toml
setup.py
tanit/__init__.py
tanit.egg-info/PKG-INFO
tanit.egg-info/SOURCES.txt
tanit.egg-info/dependency_links.txt
tanit.egg-info/entry_points.txt
tanit.egg-info/requires.txt
tanit.egg-info/top_level.txt
tanit/common/__init__.py
tanit/common/config/__init__.py
tanit/common/config/config.py
tanit/common/core/__init__.py
tanit/common/core/exception.py
tanit/common/model/__init__.py
tanit/common/model/execution_type.py
tanit/common/model/job.py
tanit/common/model/task.py
tanit/common/model/worker.py
tanit/common/utils/__init__.py
tanit/common/utils/glob.py
tanit/common/utils/utils.py
tanit/filesystem/__init__.py
tanit/filesystem/config.py
tanit/filesystem/filesystem.py
tanit/filesystem/filesystem_factory.py
tanit/filesystem/ioutils.py
tanit/filesystem/gcp/__init__.py
tanit/filesystem/gcp/filesystem.py
tanit/filesystem/hdfs/__init__.py
tanit/filesystem/hdfs/filesystem.py
tanit/filesystem/local/__init__.py
tanit/filesystem/local/local_filesystem.py
tanit/filesystem/local/remote_filesystem.py
tanit/filesystem/s3/__init__.py
tanit/filesystem/s3/filesystem.py
tanit/master/__init__.py
tanit/master/client/__init__.py
tanit/master/client/__main__.py
tanit/master/client/client.py
tanit/master/config/__init__.py
tanit/master/config/config.py
tanit/master/core/__init__.py
tanit/master/core/dispatcher.py
tanit/master/core/master.py
tanit/master/core/scheduler.py
tanit/master/core/execution/__init__.py
tanit/master/core/execution/execution_job.py
tanit/master/core/execution/execution_manager.py
tanit/master/core/execution/execution_state.py
tanit/master/core/execution/job_factory.py
tanit/master/core/worker/__init__.py
tanit/master/core/worker/worker.py
tanit/master/core/worker/worker_decommissioner.py
tanit/master/core/worker/worker_factory.py
tanit/master/core/worker/worker_manager.py
tanit/master/core/worker/worker_monitor.py
tanit/master/server/__init__.py
tanit/master/server/__main__.py
tanit/master/server/handler.py
tanit/master/server/server.py
tanit/master/standalone/__init__.py
tanit/master/standalone/master.py
tanit/master/standalone/worker.py
tanit/thrift/__init__.py
tanit/thrift/master/__init__.py
